{
    "AX": {
        "error": 0.04473093613992321, 
        "fit": "average", 
        "value": -0.10052490491714132
    }, 
    "CDD": {
        "error": 0.0002095712491984228, 
        "fit": "average", 
        "value": 0.00020882046325520302
    }, 
    "H1": {
        "error": 0.10683052726272248, 
        "fit": "average", 
        "value": 0.030701736415452933
    }, 
    "H2": {
        "error": 0.10044041751595827, 
        "fit": "average", 
        "value": 0.012076948396861553
    }, 
    "L1": {
        "error": 0.0854388694350351, 
        "fit": "average", 
        "value": -0.0694179928010399
    }, 
    "L2": {
        "error": 0.11028455404244726, 
        "fit": "average", 
        "value": 0.021115550753291183
    }
}