{
    "AX": {
        "error": 0.04294733389846449, 
        "fit": "average", 
        "value": -0.08119667779866849
    }, 
    "CDD": {
        "error": 6.231292691755998e-05, 
        "fit": "average", 
        "value": 3.183238732162863e-05
    }, 
    "H1": {
        "error": 0.10505995441351847, 
        "fit": "average", 
        "value": -0.05406868579372278
    }, 
    "H2": {
        "error": 0.09314936289140882, 
        "fit": "average", 
        "value": -0.019124111944698114
    }, 
    "L1": {
        "error": 0.09318012891219095, 
        "fit": "average", 
        "value": -0.10961821218421519
    }, 
    "L2": {
        "error": 0.1475065562916486, 
        "fit": "average", 
        "value": -0.003682253691248405
    }
}