{
    "AX": {
        "error": 0.05399218256995001, 
        "fit": "average", 
        "value": -0.09538388911646624
    }, 
    "CDD": {
        "error": 6.65749889317885e-05, 
        "fit": "average", 
        "value": 2.928579633589834e-05
    }, 
    "H1": {
        "error": 0.0988101728534788, 
        "fit": "average", 
        "value": 0.023708175273065495
    }, 
    "H2": {
        "error": 0.10967744550915574, 
        "fit": "average", 
        "value": -0.002262349011963469
    }, 
    "L1": {
        "error": 0.0850264539744738, 
        "fit": "average", 
        "value": -0.09455881538476957
    }, 
    "L2": {
        "error": 0.11921475138025296, 
        "fit": "average", 
        "value": 0.009772387701698373
    }
}