{
    "AX": {
        "error": 0.01043476350556634, 
        "filter_outliers_dict": {
            "filter_outliers": true, 
            "iterations": 1, 
            "std_devs": 2
        }, 
        "fit": "average", 
        "value": -0.1032466963065114
    }, 
    "H1": {
        "error": 0.012783968741423846, 
        "filter_outliers_dict": {
            "filter_outliers": true, 
            "iterations": 1, 
            "std_devs": 2
        }, 
        "fit": "average", 
        "value": -0.1494898086559401
    }, 
    "H2": {
        "error": 0.00918205439581959, 
        "filter_outliers_dict": {
            "filter_outliers": true, 
            "iterations": 1, 
            "std_devs": 2
        }, 
        "fit": "average", 
        "value": -0.16318738448280637
    }, 
    "L1": {
        "error": 0.009514766493534738, 
        "filter_outliers_dict": {
            "filter_outliers": true, 
            "iterations": 1, 
            "std_devs": 2
        }, 
        "fit": "average", 
        "value": -0.6695854073190758
    }, 
    "L2(CDD)": {
        "error": 0.0, 
        "filter_outliers_dict": {
            "filter_outliers": true, 
            "iterations": 1, 
            "std_devs": 2
        }, 
        "fit": "average", 
        "value": 0.0
    }
}